<?xml version='1.0' standalone='yes'?>
<extensions>
  <details>
    <title lang="EN">Philippe's Player Groups plugin - development</title>
  </details>
  <plugins>
    <plugin name="Groups" version="0.1.8" maxTarget="7.*" minTarget="7.7">
      <title lang="EN">Player Groups</title>
      <email>philippe_44@outlook.com</email>
      <sha>78299aa52d17a8b97265c427f293b69f98ac0bbb</sha>
      <desc lang="EN">Virtual players for dynamic grouping</desc>
      <creator>Philippe</creator>
      <url>http://downloads.sourceforge.net/project/lms-groups/dev/Groups-0.1.8.zip</url>
      <link>http://github.com/philippe44/LMS-Groups</link>
    </plugin>
  </plugins>
</extensions>
